ipyevents/__init__.py
ipyevents/_version.py
ipyevents/events.py
ipyevents/labextension/package.json
ipyevents/labextension/static/122.77ed9a0efa0937d651c2.js
ipyevents/labextension/static/509.bdab21a3fd873df14e82.js
ipyevents/labextension/static/884.0506464c462741a85cbf.js
ipyevents/labextension/static/remoteEntry.32d44f4437ccaeff44cd.js
ipyevents/labextension/static/style.js
ipyevents/labextension/static/third-party-licenses.json
ipyevents/nbextension/__init__.py
ipyevents/nbextension/static/extension.js
ipyevents/nbextension/static/index.js
ipyevents/nbextension/static/index.js.map
ipyevents/tests/test_events.py
ipyevents-2.0.3.data/data/share/jupyter/labextensions/ipyevents/package.json
ipyevents-2.0.3.data/data/share/jupyter/labextensions/ipyevents/static/122.77ed9a0efa0937d651c2.js
ipyevents-2.0.3.data/data/share/jupyter/labextensions/ipyevents/static/509.bdab21a3fd873df14e82.js
ipyevents-2.0.3.data/data/share/jupyter/labextensions/ipyevents/static/884.0506464c462741a85cbf.js
ipyevents-2.0.3.data/data/share/jupyter/labextensions/ipyevents/static/remoteEntry.32d44f4437ccaeff44cd.js
ipyevents-2.0.3.data/data/share/jupyter/labextensions/ipyevents/static/style.js
ipyevents-2.0.3.data/data/share/jupyter/labextensions/ipyevents/static/third-party-licenses.json
ipyevents-2.0.3.data/data/etc/jupyter/nbconfig/notebook.d/ipyevents.json
ipyevents-2.0.3.dist-info/METADATA
ipyevents-2.0.3.dist-info/WHEEL
ipyevents-2.0.3.dist-info/licenses/LICENSE.md
ipyevents-2.0.3.dist-info/RECORD
