Metadata-Version: 2.4
Name: ipyevents
Version: 2.0.3
Summary: A custom widget for returning mouse and keyboard events to Python
Project-URL: Homepage, https://github.com/mwcraig/ipyevents
Author-email: Matt Craig <mattwcraig@gmail.com>
License: BSD 3-clause
License-File: LICENSE.md
Keywords: IPython,Jupyter,Widgets
Classifier: Framework :: Jupyter
Classifier: Intended Audience :: Developers
Classifier: Intended Audience :: Science/Research
Classifier: License :: OSI Approved :: BSD License
Classifier: Programming Language :: Python
Classifier: Programming Language :: Python :: 3
Classifier: Programming Language :: Python :: 3.6
Classifier: Programming Language :: Python :: 3.7
Classifier: Programming Language :: Python :: 3.8
Classifier: Programming Language :: Python :: 3.9
Requires-Python: >=3.9
Requires-Dist: ipywidgets>=7.6.0
Provides-Extra: docs
Requires-Dist: jupyterlab>=3; extra == 'docs'
Requires-Dist: nbsphinx; extra == 'docs'
Requires-Dist: sphinx; extra == 'docs'
Provides-Extra: test
Requires-Dist: nbval; extra == 'test'
Requires-Dist: pytest; extra == 'test'
Requires-Dist: pytest-cov; extra == 'test'
